warc2graph/__init__.py
warc2graph/cli.py
warc2graph/graphs.py
warc2graph/linkextraction.py
warc2graph/networks.py
warc2graph/warc2graph.py
warc2graph-0.2.dist-info/COPYING
warc2graph-0.2.dist-info/COPYING.LGPL
warc2graph-0.2.dist-info/METADATA
warc2graph-0.2.dist-info/WHEEL
warc2graph-0.2.dist-info/entry_points.txt
warc2graph-0.2.dist-info/top_level.txt
warc2graph-0.2.dist-info/RECORD
