Metadata-Version: 2.1
Name: warc2graph
Version: 0.2
Summary: Warc2graph extracts a graph data structure from WARC files.
Home-page: https://github.com/dla-marbach/warc2graph
Author: Pascal Hein, Mona Ulrich, Claus-Michael Schlesinger, André Blessing, Evelyne Dinulescu-Roth
Author-email: pascal.hein@ilw.uni-stuttgart.de
License: LGPL v3
Classifier: Programming Language :: Python :: 3
Classifier: Programming Language :: Python :: 3.6
Classifier: Programming Language :: Python :: 3.7
Classifier: Programming Language :: Python :: 3.8
Classifier: Programming Language :: Python :: 3.9
Classifier: License :: OSI Approved :: GNU Library or Lesser General Public License (LGPL)
Classifier: License :: OSI Approved :: GNU Lesser General Public License v3 (LGPLv3)
Classifier: Operating System :: OS Independent
Classifier: Topic :: Scientific/Engineering :: Information Analysis
Classifier: Topic :: Text Processing :: Markup :: HTML
Requires-Python: >=3.6
License-File: COPYING
License-File: COPYING.LGPL
Requires-Dist: beautifulsoup4 (>=4.9.3)
Requires-Dist: matplotlib (>=3.3.3)
Requires-Dist: networkx (>=2.5)
Requires-Dist: selenium (>=3.141.0)
Requires-Dist: setuptools (>=51.0.0)
Requires-Dist: warcio (>=1.7.4)
Requires-Dist: webdriver-manager (>=3.3.0)
Requires-Dist: trafilatura (>=0.9.0)
Requires-Dist: lxml (>=4.6.0)
Requires-Dist: numpy (==1.19.5) ; python_version < "3.7"
